telecomfaker/__init__.py
telecomfaker/cli.py
telecomfaker/faker.py
telecomfaker/models.py
telecomfaker/providers.py
telecomfaker/data/__init__.py
telecomfaker/data/telecom_data.json
telecomfaker/providers/__init__.py
telecomfaker/providers/base.py
telecomfaker/providers/local_json.py
telecomfaker-0.1.1.dist-info/METADATA
telecomfaker-0.1.1.dist-info/WHEEL
telecomfaker-0.1.1.dist-info/entry_points.txt
telecomfaker-0.1.1.dist-info/top_level.txt
telecomfaker-0.1.1.dist-info/RECORD
