Metadata-Version: 2.4
Name: telecomfaker
Version: 0.1.1
Summary: A Python package for generating realistic telecom operator test data
Home-page: https://github.com/StefanStuehrmann/telecomfaker
Author: Stefan Stuehrmann
Author-email: stefan.stuehrmann@outlook.com
Project-URL: Bug Tracker, https://github.com/StefanStuehrmann/telecomfaker/issues
Classifier: Programming Language :: Python :: 3
Classifier: Programming Language :: Python :: 3.8
Classifier: Programming Language :: Python :: 3.9
Classifier: Programming Language :: Python :: 3.10
Classifier: License :: OSI Approved :: MIT License
Classifier: Operating System :: OS Independent
Classifier: Development Status :: 4 - Beta
Classifier: Intended Audience :: Developers
Classifier: Topic :: Software Development :: Testing
Classifier: Topic :: Communications
Requires-Python: >=3.8
Requires-Dist: pydantic<=2.11.3,>=1.10.8
Requires-Dist: setuptools>=42.0.0
Dynamic: author
Dynamic: author-email
Dynamic: classifier
Dynamic: description
Dynamic: description-content-type
Dynamic: home-page
Dynamic: project-url
Dynamic: requires-dist
Dynamic: requires-python
Dynamic: summary
